Pharmalyzer/ADME.py
Pharmalyzer/__init__.py
Pharmalyzer/chembl_client.py
Pharmalyzer/cleaner.py
Pharmalyzer/drug_rules.py
Pharmalyzer/encoder.py
Pharmalyzer/feature_selection.py
Pharmalyzer/filtering.py
Pharmalyzer/integrate.py
Pharmalyzer/outliers.py
Pharmalyzer/qsar.py
Pharmalyzer/scaler.py
Pharmalyzer/similarity.py
Pharmalyzer/toxicity.py
pharmalyzer-0.1.0.dist-info/licenses/Licence.txt
pharmalyzer-0.1.0.dist-info/METADATA
pharmalyzer-0.1.0.dist-info/WHEEL
pharmalyzer-0.1.0.dist-info/top_level.txt
pharmalyzer-0.1.0.dist-info/RECORD
