Metadata-Version: 2.4
Name: Pharmalyzer
Version: 0.1.0
Summary: Cheminformatics toolkit for property calculation, filtering, and QSAR modeling
Author: [Sorour Hassani]
Author-email: Sorour Hassani <s.hassani@alum.semnan.ac.ir>
License: MIT
Requires-Python: >=3.8
License-File: Licence.txt
Requires-Dist: rdkit
Requires-Dist: pandas
Requires-Dist: numpy
Requires-Dist: scikit-learn
Requires-Dist: matplotlib
Dynamic: author
Dynamic: license-file
